freshservice_mcp/__init__.py
freshservice_mcp/server.py
freshservice_mcp-1.0.0.dist-info/licenses/LICENSE
freshservice_mcp-1.0.0.dist-info/METADATA
freshservice_mcp-1.0.0.dist-info/WHEEL
freshservice_mcp-1.0.0.dist-info/entry_points.txt
freshservice_mcp-1.0.0.dist-info/top_level.txt
freshservice_mcp-1.0.0.dist-info/RECORD
