Metadata-Version: 2.4
Name: freshservice-mcp
Version: 1.0.0
Summary: An MCP server for Freshservice
Author-email: Gopi Krishnan <gopi@effy.co.in>, Maanaesh Swamy <maanaesh.s@effy.co.in>, Vijay Ragunath <vijay.r@effy.co.in>
Requires-Python: >=3.13
License-File: LICENSE
Requires-Dist: build>=1.2.2.post1
Requires-Dist: httpx==0.28.1
Requires-Dist: mcp[cli]>=1.3.0
Requires-Dist: pydantic>=2.10.6
Dynamic: license-file
